{
	"animations": [
		{
			"offsets": [
				0,
				0
			],
			"loop": true,
			"fps": 24,
			"anim": "idle",
			"indices": [],
			"name": "Idle"
		},
		{
			"offsets": [
				-54,
				-56
			],
			"loop": true,
			"fps": 24,
			"anim": "singDOWN",
			"indices": [],
			"name": "Down"
		},
		{
			"offsets": [
				-95,
				2
			],
			"loop": true,
			"fps": 24,
			"anim": "singUP",
			"indices": [],
			"name": "Up"
		},
		{
			"loop": true,
			"offsets": [
				281,
				-76
			],
			"anim": "singLEFT",
			"fps": 24,
			"name": "Right",
			"indices": []
		},
		{
			"loop": true,
			"offsets": [
				-9,
				31
			],
			"anim": "singRIGHT",
			"fps": 24,
			"name": "Left",
			"indices": []
		},
		{
			"offsets": [
				-54,
				-56
			],
			"loop": false,
			"fps": 24,
			"anim": "singDOWNmiss",
			"indices": [],
			"name": "Down"
		},
		{
			"offsets": [
				-95,
				2
			],
			"loop": false,
			"fps": 24,
			"anim": "singUPmiss",
			"indices": [],
			"name": "Up"
		},
		{
			"offsets": [
				281,
				-76
			],
			"loop": false,
			"fps": 24,
			"anim": "singLEFTmiss",
			"indices": [],
			"name": "Right"
		},
		{
			"offsets": [
				-8,
				31
			],
			"loop": false,
			"fps": 24,
			"anim": "singRIGHTmiss",
			"indices": [],
			"name": "Left"
		}
	],
	"no_antialiasing": false,
	"image": "characters/TrickyPhase0.5",
	"position": [
		-200,
		100
	],
	"healthicon": "TrickyPhase0.5",
	"flip_x": false,
	"healthbar_colors": [
		24,
		95,
		64
	],
	"camera_position": [
		0,
		0
	],
	"sing_duration": 6.1,
	"scale": 1
}