{
	"animations": [
		{
			"offsets": [
				94,
				22
			],
			"loop": true,
			"fps": 24,
			"anim": "singLEFT",
			"indices": [],
			"name": "Sing Left"
		},
		{
			"offsets": [
				-24,
				-42
			],
			"loop": true,
			"fps": 24,
			"anim": "singDOWN",
			"indices": [],
			"name": "Sing Down"
		},
		{
			"offsets": [
				63,
				15
			],
			"loop": true,
			"fps": 24,
			"anim": "singUP",
			"indices": [],
			"name": "Sing Up"
		},
		{
			"offsets": [
				-68,
				-60
			],
			"loop": true,
			"fps": 24,
			"anim": "singRIGHT",
			"indices": [],
			"name": "Sing Right"
		},
		{
			"offsets": [
				0,
				0
			],
			"loop": true,
			"fps": 24,
			"anim": "idle",
			"indices": [],
			"name": "Idle"
		}
	],
	"no_antialiasing": false,
	"image": "characters/old/TrickyPhase0",
	"position": [
		0,
		150
	],
	"healthicon": "TrickyPhase0old",
	"flip_x": false,
	"healthbar_colors": [
		255,
		255,
		255
	],
	"camera_position": [
		0,
		0
	],
	"sing_duration": 6.1,
	"scale": 1
}